{
  "name": "t:sections.header.name",
  "type": "header",
  "sections": {
    "lh-announcement": {
      "type": "lh-announcement-bar",
      "blocks": {
        "announcement-1": {
          "type": "announcement",
          "settings": {
            "text": "FREE SHIPPING & RETURNS"
          }
        },
        "announcement-2": {
          "type": "announcement",
          "settings": {
            "text": "101-NIGHT GUARANTEE"
          }
        }
      },
      "block_order": [
        "announcement-1",
        "announcement-2"
      ]
    },
    "lh-header": {
      "type": "lh-header",
      "settings": {}
    }
  },
  "order": [
    "lh-announcement",
    "lh-header"
  ]
}
